README.txt
ez_setup.py
mzsudoku.py
setup.py
mzsudoku.egg-info/PKG-INFO
mzsudoku.egg-info/SOURCES.txt
mzsudoku.egg-info/dependency_links.txt
mzsudoku.egg-info/top_level.txt