Metadata-Version: 1.0
Name: mzsudoku
Version: 1.0.0
Summary: Module/script to solve classical 9x9 Sudoku step by step
Home-page: http://www.github.com/zvolsky/sudoku/
Author: Zvolsky Mirek
Author-email: mirek.zvolsky@gmail.com
License: open source GPL
Keywords: sudoku
Platform: UNKNOWN
